two_iamyuan/__init__.py
two_iamyuan-0.1.2.dist-info/WHEEL
two_iamyuan-0.1.2.dist-info/entry_points.txt
two_iamyuan-0.1.2.dist-info/METADATA
two_iamyuan-0.1.2.dist-info/RECORD
