Metadata-Version: 2.3
Name: two-iamyuan
Version: 0.1.2
Summary: Add your description here
Author: Y4
Author-email: Y4 <2420086222@qq.com>
Requires-Dist: mcp[cli]>=1.14.1
Requires-Python: >=3.13
